[
  {
    "id": "tab-iot-main",
    "type": "tab",
    "label": "Smart City IoT",
    "disabled": false,
    "info": ""
  },

  {
    "id": "cfg-mqtt",
    "type": "mqtt-broker",
    "name": "Mosquitto",
    "broker": "mosquitto",
    "port": "1883",
    "clientid": "nodered-client",
    "autoConnect": true,
    "usetls": false,
    "protocolVersion": "4",
    "keepalive": "60",
    "cleansession": true,
    "autoUnsubscribe": true,
    "birthTopic": "",
    "birthQos": "0",
    "birthRetain": false,
    "birthPayload": "",
    "closeTopic": "",
    "closeQos": "0",
    "closeRetain": false,
    "closePayload": "",
    "willTopic": "",
    "willQos": "0",
    "willRetain": false,
    "willPayload": "",
    "sessionExpiry": ""
  },

  {
    "id": "mqtt-sensor",
    "type": "mqtt in",
    "z": "tab-iot-main",
    "name": "MQTT Sensor Data",
    "topic": "smartcity/environment/+/sensor",
    "qos": "1",
    "datatype": "auto-detect",
    "broker": "cfg-mqtt",
    "nl": false,
    "rap": false,
    "rh": 0,
    "inputs": 0,
    "x": 120,
    "y": 100,
    "wires": [["parse-sensor"]]
  },

  {
    "id": "mqtt-anomaly",
    "type": "mqtt in",
    "z": "tab-iot-main",
    "name": "MQTT Anomaly",
    "topic": "smartcity/environment/+/anomaly",
    "qos": "2",
    "datatype": "auto-detect",
    "broker": "cfg-mqtt",
    "nl": false,
    "rap": false,
    "rh": 0,
    "inputs": 0,
    "x": 120,
    "y": 260,
    "wires": [["parse-anomaly"]]
  },

  {
    "id": "parse-sensor",
    "type": "json",
    "z": "tab-iot-main",
    "name": "Parse JSON",
    "property": "payload",
    "action": "obj",
    "pretty": false,
    "x": 310,
    "y": 100,
    "wires": [["fn-sensor"]]
  },

  {
    "id": "parse-anomaly",
    "type": "json",
    "z": "tab-iot-main",
    "name": "Parse JSON",
    "property": "payload",
    "action": "obj",
    "pretty": false,
    "x": 310,
    "y": 260,
    "wires": [["fn-anomaly"]]
  },

  {
    "id": "fn-sensor",
    "type": "function",
    "z": "tab-iot-main",
    "name": "Siapkan data reading",
    "func": "var data = msg.payload;\n\n// ambil zone_id dari topic: smartcity/environment/{zone_id}/sensor\nvar parts = msg.topic.split('/');\ndata.zone_id = parseInt(parts[2]) || data.zone_id;\n\n// pastikan recorded_at ada\nif (!data.recorded_at) {\n    data.recorded_at = new Date().toISOString();\n}\n\nmsg.payload = data;\nmsg.headers = {'Content-Type': 'application/json'};\nreturn msg;",
    "outputs": 1,
    "timeout": 0,
    "noerr": 0,
    "initialize": "",
    "finalize": "",
    "libs": [],
    "x": 510,
    "y": 100,
    "wires": [["http-reading"]]
  },

  {
    "id": "fn-anomaly",
    "type": "function",
    "z": "tab-iot-main",
    "name": "Siapkan data alert",
    "func": "var data = msg.payload;\n\nvar parts = msg.topic.split('/');\nvar zoneId = parseInt(parts[2]) || data.zone_id;\n\nmsg.payload = {\n    zone_id:    zoneId,\n    alert_type: data.alert_type || 'aqi_high',\n    severity:   data.severity   || 'high',\n    message:    data.message    || 'AQI melebihi batas aman',\n    value:      data.aqi        || null,\n    threshold:  200\n};\nmsg.headers = {'Content-Type': 'application/json'};\nreturn msg;",
    "outputs": 1,
    "timeout": 0,
    "noerr": 0,
    "initialize": "",
    "finalize": "",
    "libs": [],
    "x": 510,
    "y": 260,
    "wires": [["http-alert"]]
  },

  {
    "id": "http-reading",
    "type": "http request",
    "z": "tab-iot-main",
    "name": "POST /api/readings",
    "method": "POST",
    "ret": "obj",
    "paytoqs": "ignore",
    "url": "http://php-environment:8002/api/readings",
    "tls": "",
    "persist": false,
    "proxy": "",
    "insecureHTTPParser": false,
    "authType": "",
    "senderr": false,
    "headers": [],
    "x": 720,
    "y": 100,
    "wires": [["debug-reading"]]
  },

  {
    "id": "http-alert",
    "type": "http request",
    "z": "tab-iot-main",
    "name": "POST /api/alerts",
    "method": "POST",
    "ret": "obj",
    "paytoqs": "ignore",
    "url": "http://php-environment:8002/api/alerts",
    "tls": "",
    "persist": false,
    "proxy": "",
    "insecureHTTPParser": false,
    "authType": "",
    "senderr": false,
    "headers": [],
    "x": 720,
    "y": 260,
    "wires": [["debug-alert"]]
  },

  {
    "id": "debug-reading",
    "type": "debug",
    "z": "tab-iot-main",
    "name": "Response Reading",
    "active": true,
    "tosidebar": true,
    "console": false,
    "tostatus": true,
    "complete": "payload",
    "targetType": "msg",
    "statusVal": "payload.risk_level",
    "statusType": "msg",
    "x": 940,
    "y": 100,
    "wires": []
  },

  {
    "id": "debug-alert",
    "type": "debug",
    "z": "tab-iot-main",
    "name": "Response Alert",
    "active": true,
    "tosidebar": true,
    "console": false,
    "tostatus": true,
    "complete": "payload",
    "targetType": "msg",
    "statusVal": "payload.success",
    "statusType": "msg",
    "x": 940,
    "y": 260,
    "wires": []
  },

  {
    "id": "inject-test",
    "type": "inject",
    "z": "tab-iot-main",
    "name": "Test (klik untuk inject data)",
    "props": [
      {"p": "payload"},
      {"p": "topic", "vt": "str"}
    ],
    "repeat": "",
    "crontab": "",
    "once": false,
    "onceDelay": 0.1,
    "topic": "smartcity/environment/1/sensor",
    "payload": "{\"zone_id\":1,\"pm25\":185.5,\"pm10\":310.2,\"no2\":0.12,\"co\":4.5,\"o3\":0.01,\"temperature\":22.3,\"humidity\":92.0,\"wind_speed\":0.3,\"aqi\":312.0,\"recorded_at\":\"2026-06-14T23:00:00+07:00\",\"inversion_active\":true}",
    "payloadType": "json",
    "x": 150,
    "y": 180,
    "wires": [["parse-sensor"]]
  },

  {
    "id": "tab-wearable",
    "type": "tab",
    "label": "Wearable Heart Rate",
    "disabled": false,
    "info": ""
  },

  {
    "id": "mqtt-wearable",
    "type": "mqtt in",
    "z": "tab-wearable",
    "name": "MQTT Heart Rate",
    "topic": "wearable/+/heartrate",
    "qos": "1",
    "datatype": "auto-detect",
    "broker": "cfg-mqtt",
    "nl": false,
    "rap": false,
    "rh": 0,
    "inputs": 0,
    "x": 120,
    "y": 100,
    "wires": [["parse-wearable"]]
  },

  {
    "id": "parse-wearable",
    "type": "json",
    "z": "tab-wearable",
    "name": "Parse JSON",
    "property": "payload",
    "action": "obj",
    "pretty": false,
    "x": 310,
    "y": 100,
    "wires": [["fn-detect-session"]]
  },

  {
    "id": "fn-detect-session",
    "type": "function",
    "z": "tab-wearable",
    "name": "Deteksi sesi aktivitas",
    "func": "var deviceId = msg.payload.device_id || 'unknown';\nvar hr       = msg.payload.heart_rate;\nvar zoneId   = msg.payload.zone_id;\nvar ts       = msg.payload.recorded_at || new Date().toISOString();\n\n// Klasifikasi aktivitas dari heart rate\nvar activity;\nif (hr < 90) {\n    activity = 'rest';\n} else if (hr < 130) {\n    activity = 'walking';\n} else {\n    activity = 'running';\n}\n\n// Ambil state sesi dari context (per device)\nvar key     = 'session_' + deviceId;\nvar session = flow.get(key) || { active: false };\n\nif (!session.active && activity !== 'rest') {\n    // Sesi dimulai\n    flow.set(key, { active: true, started_at: ts });\n    msg.payload = { device_id: deviceId, zone_id: zoneId, activity_type: activity, started_at: ts };\n    msg.headers = { 'Content-Type': 'application/json' };\n    return [msg, null];\n}\n\nif (session.active && activity === 'rest') {\n    // Sesi selesai\n    flow.set(key, { active: false });\n    msg.payload = { device_id: deviceId, zone_id: zoneId, ended_at: ts };\n    msg.headers = { 'Content-Type': 'application/json' };\n    return [null, msg];\n}\n\n// Tidak ada perubahan state\nreturn [null, null];",
    "outputs": 2,
    "timeout": 0,
    "noerr": 0,
    "initialize": "",
    "finalize": "",
    "libs": [],
    "x": 510,
    "y": 100,
    "wires": [["http-session-start"], ["http-session-end"]]
  },

  {
    "id": "http-session-start",
    "type": "http request",
    "z": "tab-wearable",
    "name": "POST /api/activity-sessions/start",
    "method": "POST",
    "ret": "obj",
    "paytoqs": "ignore",
    "url": "http://php-citizen:8000/api/activity-sessions/start",
    "tls": "",
    "persist": false,
    "proxy": "",
    "insecureHTTPParser": false,
    "authType": "",
    "senderr": false,
    "headers": [],
    "x": 760,
    "y": 60,
    "wires": [["debug-session-start"]]
  },

  {
    "id": "http-session-end",
    "type": "http request",
    "z": "tab-wearable",
    "name": "POST /api/activity-sessions/end",
    "method": "POST",
    "ret": "obj",
    "paytoqs": "ignore",
    "url": "http://php-citizen:8000/api/activity-sessions/end",
    "tls": "",
    "persist": false,
    "proxy": "",
    "insecureHTTPParser": false,
    "authType": "",
    "senderr": false,
    "headers": [],
    "x": 760,
    "y": 140,
    "wires": [["debug-session-end"]]
  },

  {
    "id": "debug-session-start",
    "type": "debug",
    "z": "tab-wearable",
    "name": "Response Start",
    "active": true,
    "tosidebar": true,
    "console": false,
    "tostatus": true,
    "complete": "payload",
    "targetType": "msg",
    "statusVal": "payload.success",
    "statusType": "msg",
    "x": 980,
    "y": 60,
    "wires": []
  },

  {
    "id": "debug-session-end",
    "type": "debug",
    "z": "tab-wearable",
    "name": "Response End",
    "active": true,
    "tosidebar": true,
    "console": false,
    "tostatus": true,
    "complete": "payload",
    "targetType": "msg",
    "statusVal": "payload.success",
    "statusType": "msg",
    "x": 980,
    "y": 140,
    "wires": []
  }
]
